[
  {
    "question": "Şüa terapiyası nədir?  ",
    "answers": [
      "Ionlaşdırıcı şüaların yalnız müalicə məqsədi ilə tətbiqi  ",
      "Günəş şüalarının müalicə məqsədi ilə tətbiqi  ",
      "Şüaların həm diaqnostika, həm terapiya məqsədi ilə tətbiqi  ",
      "Lazer şüalarının müalicə məqsədi ilə tətbiqi  ",
      "Şüaların yalnız diaqnostika məqsədi ilə tətbiqi  "
    ]
  },
  {
    "question": "Təbii radioaktivliyin kəşf edildiyi tarix:  ",
    "answers": [
      "1896  ",
      "1696  ",
      "2000  ",
      "1999  ",
      "1996  "
    ]
  },
  {
    "question": "Təbii radioaktivliyin banisi kimdir?  ",
    "answers": [
      "Anri Bekkerel  ",
      "Mariya Küri  ",
      "Frederic Jolio  ",
      "K. Anderson  ",
      "Lui Paster  "
    ]
  },
  {
    "question": "Radioaktivlik nədir?  ",
    "answers": [
      "hər hansı elementin əlavə təsir olmadan özündən enerji xaric etmək qabiliyyəti  ",
      "hər hansı elementin həcmi  ",
      "hər hansı elementin işıq vermək qabiliyyəti  ",
      "hər hansı elementin istilik vermək qabiliyyəti  ",
      "hər hansı elementin sürətlə hərəkət etmək qabiliyyəti  "
    ]
  },
  {
    "question": "Bədxassəli şişlərin müalicəsində hansı şüalardan istifadə olunur?   ",
    "answers": [
      "İonlaşdırıcı şüalar  ",
      "Radiodalğalar  ",
      "Görülən işıq şüaları  ",
      "Ultrabənövşəyi şüalar  ",
      "İnfraqırmızı istilik şüaları  "
    ]
  },
  {
    "question": "Süni izotopların kəşf olunma tarixi?  ",
    "answers": [
      "1934  ",
      "1956  ",
      "1941  ",
      "2000  ",
      "1434  "
    ]
  },
  {
    "question": "İonlaşdırıcı şüaların təsirindən toxumalarda əmələ gələn dəyişikliklər hansılardır?    2   ",
    "answers": [
      "biofiziki, biokimyəvi  ",
      "yalnız fiziki  ",
      "Texniki, kimyəvi  ",
      "Bioloji, texniki  ",
      "Fiziki, termiki  "
    ]
  },
  {
    "question": "İonlaşdırıcı qabiliyyətə malik şüaları göstərin:  ",
    "answers": [
      "Kvant və korpuskulyar təbiətli şüalar  ",
      "Lazer və günəş şüaları  ",
      "Ultrabənövşəyi və lazer şüaları  ",
      "Görünən işıq şüaları və səs dalğaları  ",
      "Infraqırmızı və radio dalğalar  "
    ]
  },
  {
    "question": "Təbii radoiaktiv ailələrinin sonu nə ilə bitir?  ",
    "answers": [
      "bəsit qurğuşun  ",
      "radioaktiv uran  ",
      "qızıl  ",
      "oksigen  ",
      "bəsit dəmir  "
    ]
  },
  {
    "question": "Aşağıdakılardan hansılar ionlaşdırıcı şüalara aiddir?  ",
    "answers": [
      "Alfa, betta, qamma  ",
      "Görünən işıq şüaları və qamma şüalar  ",
      "Lazer şüaları və infraqırımızı şüalar  ",
      "Ultrabənövşəyi şüalar və beta şüalar  ",
      "Infraqırmızı şüalar və alfa şüalar  "
    ]
  },
  {
    "question": "Bədəninə radionuklid yerləşdirilən xəstə hansı palatada saxlanılır?  ",
    "answers": [
      "Aktiv  ",
      "Sadə  ",
      "evə buraxılır  ",
      "Lüks  ",
      "Adi  "
    ]
  },
  {
    "question": "Braxiterapiya alan xəstələr hansı palatada yerləşdirilir?  ",
    "answers": [
      "Aktiv  ",
      "Həm adi, həm aktiv  ",
      "böyük sahəli  ",
      "İşıqlı  ",
      "Adi  "
    ]
  },
  {
    "question": "Distansion şüa müalicəsi zamanı xəstələr hansı palatada yerləşdirilir?  ",
    "answers": [
      "Adi  ",
      "böyük sahəli   3   ",
      "Həm adi, həm aktiv  ",
      "qaranlıq  ",
      "Aktiv  "
    ]
  },
  {
    "question": "Nə üçün ionlaşdırıcı şüaların təsirindən qorunmalıyıq?  ",
    "answers": [
      "orqanizmə zədələyici bioloji təsiri var  ",
      "bölünmə proseslərini sürətləndirir  ",
      "bəzi üzvlərin funksiyasını azaldır  ",
      "qorunmağa ehtiyac yoxdur  ",
      "üzvlərin sürətlə böyüməsinə gətirir  "
    ]
  },
  {
    "question": "Qoruyucu ekran nədir?  ",
    "answers": [
      "şüa selinin qarşısını ala bilən maneə  ",
      "şüa selini yönləndirən ekran  ",
      "şüa enerjisini səpələyən ekran  ",
      "güllə keçirməyən geyim  ",
      "şüanın təsirini gücləndirən vasitə  "
    ]
  },
  {
    "question": "Şüalanma dozasının intensivliyinin məsafədən asılılığı:   ",
    "answers": [
      "şüalanmanın intensivliyi məsafənin kvadratı ilə tərs mütənasibdir  ",
      "şüalanmanın intensivliyi məsafədən asılı deyil  ",
      "məsafədən asılılıq ancaq kvant təbiətli şüalara aiddir  ",
      "şüalanmanın intensivliyi məsafənin kubu qədər artır  ",
      "məsafə artdıqda şüalanma artır  "
    ]
  },
  {
    "question": "Tormozlanmış şüa nədir?  ",
    "answers": [
      "qısadalğalı rentgen şüadır  ",
      "uzundalğalı qamma şüadır  ",
      "qısadalğalı qamma şüadır  ",
      "qısadalğalı proton şüadır  ",
      "uzundalğalı rentgen şüadır  "
    ]
  },
  {
    "question": "Emanasiya nədir?   ",
    "answers": [
      "təbii radioaktiv ailələrin qaz məhsulu  ",
      "süni qazların cəmi  ",
      "radioaktiv metalların qarışığı  ",
      "su molekulunun kütləsi  ",
      "parçalanmanın son məhsulu  "
    ]
  },
  {
    "question": "Qrey nəyin ölçü vahididir?  ",
    "answers": [
      "Udulan şüa dozasının  ",
      "Xaric olan dozanın   ",
      "Ekvivalent şüa dozasının   4   ",
      "Şüanın ekspozisiya dozasının  ",
      "Şüanın aktivlik dozasının  "
    ]
  },
  {
    "question": "Bekkerel nəyin ölçü vahididr?  ",
    "answers": [
      "elementin aktivliyinin  ",
      "Ekvivalent dozanın  ",
      "Dərinlik dozasının  ",
      "Udulma dozasının  ",
      "Ekspozisiya dozasının  "
    ]
  },
  {
    "question": "Ekvivalent dozanın ölçü vahidi nədir?  ",
    "answers": [
      "Zivert  ",
      "Bekkerel  ",
      "Kulon  ",
      "Amper  ",
      "Qrey  "
    ]
  },
  {
    "question": "Zivert ilə ölçülən doza hansıdır?   ",
    "answers": [
      "Ekvivalent doza  ",
      "Ekspozisiya dozası  ",
      "Cəmi ocaq dozası  ",
      "Aktivlik dozası  ",
      "inteqral doza  "
    ]
  },
  {
    "question": "Şüalanmaya həssaslıqdan asılı olaraq, şişlər:  ",
    "answers": [
      "Radiohəssas və radiorezistent olur  ",
      "Yumşaq, sərt və infiltrativ olur  ",
      "endofit və ekzofit olur  ",
      "Hiperhəssas və hiperdayanıqlı olur  ",
      "Hipohəssas və ekzofit olur  "
    ]
  },
  {
    "question": "Şüaya həssaslıq nədir?  ",
    "answers": [
      "udulan şüa dozasına bioloji obyektin verdiyi cavab  ",
      "sistemlərin iş ahəngi  ",
      "dərinin şüalanmaya cavab reaksiyası  ",
      "sinir sistemin bərpa prosesi  ",
      "səthi və dərinlik dozalarının nisbəti  "
    ]
  },
  {
    "question": "Dozimetr nədir?   ",
    "answers": [
      "şüa enerjisinin miqdarını təyin edən cihaz   5   ",
      "istiliyi ölçən cihaz  ",
      "məsafəni ölçən cihaz  ",
      "işığın sürətini təyin edən cihaz  ",
      "şüanın təzyiqini ölçən cihaz  "
    ]
  },
  {
    "question": "Hansı şiş daha radiohəssasdır?  ",
    "answers": [
      "Limfoma  ",
      "Osteogen sarkoma  ",
      "böyrək xərçəngi  ",
      "fibrosarkoma  ",
      "neyrogen şiş  "
    ]
  },
  {
    "question": "Hansı şiş daha radiorezistentdir?  ",
    "answers": [
      "Osteosarkoma  ",
      "süd vəzi xərçəngi  ",
      "Seminoma  ",
      "plazmositoma  ",
      "limfoma  "
    ]
  },
  {
    "question": "Şüaya həssaslığı artırmaq üçün istifadə olunan tədbirı göstərin:  ",
    "answers": [
      "Hiperqlikemiya  ",
      "Cərrahi müdaxilə  ",
      "Kortikosteroidlərin istifadəsi  ",
      "Vitaminlərin istifadəsi  ",
      "Antibotiklərin istifadəsi  "
    ]
  },
  {
    "question": "Şüaya həssaslığı artırmaq üçün istifadə olunan tədbirlərdən biri:  ",
    "answers": [
      "Elektron-akseptor birləşmələrin istifadəsi  ",
      "Antidepressantların istifadəsi  ",
      "Güclü qidalanma  ",
      "Antibiotiklərin istifadəsi  ",
      "Kortikosteroidlərin istifadəsi  "
    ]
  },
  {
    "question": "1 Qr udulma doza nədir?  ",
    "answers": [
      "1 kq toxumaya 1 C (Coul) enerjinin ötürülməsidir   ",
      "dərinlik dozasının səthi dozaya olan nisbətidir  ",
      "saniyədə bir parçalanma aktıdır  ",
      "səthi toxumalara çatan şüalanma energisidir  ",
      "vahid zaman ərzində verilən şüanın miqdarıdır  "
    ]
  },
  {
    "question": "Şüaya həssaslığa təsir edən preparat hansıdır?  ",
    "answers": [
      "5 flüorurosil  ",
      "Sulfokamfokain  ",
      "Vitamin C  ",
      "Aktovegin   6   ",
      "Aspirin kardio  "
    ]
  },
  {
    "question": "Hüceyrələrin şüalanmaya ən həssas olduğu bölünmə fazası hansıdır?   ",
    "answers": [
      "M  ",
      "S  ",
      "presintetik  ",
      "G0  ",
      "G1  "
    ]
  },
  {
    "question": "Aşağıdakılardan hansı şişlər radiohəssasdır?   ",
    "answers": [
      "Limfoma, seminoma  ",
      "fibrosarkoma , xondrosarkoma  ",
      "seminoma, osteosarkoma  ",
      "neyrogen şiş, osteosarkoma  ",
      "leyomiosarkoma, fibrosarkomalar  "
    ]
  },
  {
    "question": "Aşağıdakılardan şüaya davamlı olanları göstərin:   ",
    "answers": [
      "Əzələ və sinir toxuması  ",
      "cinsi hüceyrələr  ",
      "Qırmızı sümük iliyi  ",
      "Piy toxuması və qanyaradıcı sistem  ",
      "Nazik bağırsaq epitelisi və birləşdirici toxuma  "
    ]
  },
  {
    "question": "Fotonun enerjisindən asılı olaraq baş verən effektləri göstərin:  ",
    "answers": [
      "Fotoeffekt, Kompton effekti, Cütlüklərin yaranma effekti  ",
      "Radioeffekt, Fotoeffekt, Cütlüklərin əmələgəlmə effekti  ",
      "Fotoeffekt, Radioeffekt, Kompton effekti  ",
      "Radioeffekt, Fotoeffekt, Dekompensasiya  ",
      "Kompton, Radioeffekt, Cütlüklərin əmələgəlmə effekti  "
    ]
  },
  {
    "question": "Ionızasiyalı kameraların iş prinsipi hansı xüsusiyyətə əsaslanır?  ",
    "answers": [
      "ionlaşdırıcı şüanın hava və qazları naqilə çevirməsinə  ",
      "şüalanmadan arterial təzyiqin artmasına  ",
      "endokrin sistemin fəaliyyətinin aktivləşməsinə  ",
      "bioloji toxumaların şüanın təsirindən sürətlə böyüməsinə  ",
      "daxili üzvlərin funksiyalarının ləngiməsinə  "
    ]
  },
  {
    "question": "Ssintilyasion dozimetrin iş prinsipi hansı xassəyə əsaslanır?  ",
    "answers": [
      "bəzi maddələrin ionlaşdırıcı şüaların təsirindən qığılcım verməsinə   7   ",
      "şüalanmadan arterial təzyiqin azalmasına  ",
      "bioloji toxumaların şüanın təsirindən sürətlə böyüməsinə  ",
      "daxili üzvlərin funksiyasının zəifləməsinə  ",
      "endokrin sistemin fəaliyyətinin zəifləməsinə  "
    ]
  },
  {
    "question": "Ekspozisiyalı doza nəyi göstərir?  ",
    "answers": [
      "foton təbiətli şüaların havada yaratdığı ionların miqdarını   ",
      "kosmosdan gələn şüalanma dozasını   ",
      "şüaya davamiyyəti   ",
      "obyekt tərəfindən udulan enerjini   ",
      "dəyişiklik yaradan gərginliyi  "
    ]
  },
  {
    "question": "Hiperfraksion şüalanma hansı rejimdə aparılır?  ",
    "answers": [
      "hər dəfə 1-1,5 Qr, gündə 2-3 dəfə, 4-6 saat intervalla  ",
      "hər dəfə 1,5 Qr, həftədə 5 dəfə  ",
      "hər dəfə 8 Qr, həftədə 1 dəfə  ",
      "hər dəfə 2-2,2 Qr, həftədə 3 dəfə  ",
      "hər dəfə 3-3,2 Qr, həftədə 3 dəfə  "
    ]
  },
  {
    "question": "Split kurslar hansılardır?  ",
    "answers": [
      "cəmi dozanın yarısında verilən 2-4 həftəlik fasilə  ",
      "fasiləsiz aparılan şüalanma  ",
      "cəmi dozanın yarısında verilən 2-4 aylıq fasilə  ",
      "cəmi dozanın yarısında verilən 2-4 günlük fasilə  ",
      "cəmi dozanın yarısında verilən 5-7 həftəlik fasilə  "
    ]
  },
  {
    "question": "Toxumalarda enerjinin fiqurlu və ya rəqəmsal paylanmasını əks edən xəritələrə:  ",
    "answers": [
      "izodoz xəritəsi deyilir  ",
      "paylanma xəritəsi deyilir  ",
      "udulma xəritəsi deyilir  ",
      "enerji xəritəsi deyilir  ",
      "izobar xəritəsi deyilir  "
    ]
  },
  {
    "question": "Hansı patologiya şüa müalicəsinə göstərişdir?  ",
    "answers": [
      "Bədxassəli şiş  ",
      "Ürək qüsuru  ",
      "Ağciyər vərəmi  ",
      "Qrip  ",
      "Pnevmoniya  "
    ]
  },
  {
    "question": "Hansı patologiya şüa müalicəsinə göstərişdir?  ",
    "answers": [
      "Sirinqomieliya  ",
      "ürək qüsuru  ",
      "Pnevmoniya  ",
      "Şəkərli diabet  ",
      "hipertoniya  "
    ]
  },
  {
    "question": "Hansı patologiya şüa müalicəsinə göstərişdir?    8   ",
    "answers": [
      "Metastazlar  ",
      "ürək qüsuru  ",
      "sistit  ",
      "Ağciyər vərəmi  ",
      "Şəkərli diabet  "
    ]
  },

  {
    "question": "Qurguşun bloklar nə üçün istifadə olunur? (  1) ətraf sağlam toxuma və orqanları qorumaq üçün   2) patoloji ocaqda şüalanma sahəsi yaratmaq üçün   3) Patoloji ocaqda dozanın artırılması üçün   4) Iri həcmli şişlərin şüalanması zamanı   5) kiçik həcmli şişlərin müalicəsi üçün  ",
    "answers": [
      "1,2  ",
      "1,5  ",
      "4,5  ",
      "3,4  ",
      "1,4  "
    ]
  },
  {
    "question": "GTV nədir?   ",
    "answers": [
      "Şişin böyük həcmi  ",
      "Planlaşdırılan hədəf həcmi  ",
      "Virtual KT simulyator  ",
      "Konvension rentgen simulyator  ",
      "Şişin görünən həcmi  "
    ]
  },
  {
    "question": "PTV nədir?  ",
    "answers": [
      "Hədəfun planlaşdırılan həcmi  ",
      "İzodoz xəritə  ",
      "Rentgen simulyator  ",
      "Kliniki hədəf həcmi  ",
      "Şişin görünən həcmi  "
    ]
  },
  {
    "question": "Simptomatik şüa terapiyasının məqsədi nədir?   ",
    "answers": [
      "Bədxassəli prosesə xas olan simptomları aradan götürmək  ",
      "şiş hüceyrələrini öldürmək  ",
      "Şişi letal zədələmək   9   ",
      "Daha həssas şiş hüceyrələri yaratmaq  ",
      "Şiş hüceyrələrinin bioloji aktivliyini artırmaq  "
    ]
  },
  {
    "question": "Palliativ şüa terapiyasının məqsədi nədir?  ",
    "answers": [
      "Şişin ölçüsünün kiçildilməsi və xəstənin vəziyyətinin yaxşılaşdırılması  ",
      "Daha həssas şiş hüceyrələrinin yaradılması  ",
      "Letal zədələnmənin əldə olunması  ",
      "Şiş hüceyrələrinin bioloji aktivliyinin artırılması  ",
      "Şişin tam reqressiyasının əldə edilməsi  "
    ]
  },
  {
    "question": "İnsan bədəninə münasibətinə görə ayırd edilən şüa növləri hansılardır?  ",
    "answers": [
      "Daxili və xarici şüalanma  ",
      "Paralel və xətli şüalanma  ",
      "Isti və soyuq şüalanma  ",
      "Yaxın və uzaq şüalanma  ",
      "Səthi və dərin şüalanma  "
    ]
  },
  {
    "question": "Müştərək şüa müalicəsi nədir?  ",
    "answers": [
      "Distansion və kontakt şüalanmanın birlikdə istifadəsi  ",
      "Radioaktiv yodla müalicə   ",
      "Cyber-knife və distansion qamma şüalanmasından birlikdə istifadə edilməsi  ",
      "protonterapiya və cərrahiyənin birlikdə istifadəsi  ",
      "Neytron terapiya və kimyəvi terapiyanın birlikdə istifadəsi  "
    ]
  },
  {
    "question": "Radioterapevtik interval yaratmağın əsas prinsipi hansıdır?  ",
    "answers": [
      "Şiş toxumasının zədələnməsini əldə edərək, ətraf sağlam toxumaları maksimum qorumaq  ",
      "Ətraf sağlam toxuma və orqanları maksimal şüalandırmaqla bədxassəli şişləri zədələmək  ",
      "Xəstənin ümumi vəziyyətini nəzərə almayaraq şişə maksimal doza çatdırmaq  ",
      "Ən qısa müddətdə yüksək doza ilə şüa terapiyasını bitirmək  ",
      "Ətraf sağlam toxuma və orqanlara təsir nəzərə alınmadan şişi şüalandırmaq  "
    ]
  },
  {
    "question": "Şüa müalicəsində istifadə edilən bloklar hansı materialdan hazırlanır? ",
    "answers": [
      "Qurğuşun  ",
      "Gümüş  ",
      "Platin  ",
      "Palladium  ",
      "Alüminium  "
    ]
  },
  {
    "question": "Hansı cihazın köməkliyi ilə rentgenterapiya aparılır?  ",
    "answers": [
      "RUM-7, GULMAY   10   ",
      "Clinac DHX, Gamma -knife  ",
      "Rokus-M, AQAT-C  ",
      "AQAT-C, Gamma-knife  ",
      "Teragam, Varian  "
    ]
  },
  {
    "question": "Əməliyyatdan qabaq aparılan şüa terapiyasın məqsədləri:  ",
    "answers": [
      "Şişin həcminin kiçilməsi, metastaz sayının azaldılması, intraoperasion disseminasiyanın  qarşısının alınması  ",
      "qanaxmanın profilaktikası məqsədilə  ",
      "Ancaq residiv və metastazların qarşısının alınması  ",
      "Ancaq şişin ölçülərinin kiçilməsi və xəstənin vəziyyətinin yaxşılaşdırılması  ",
      "Xəstənin vəziyyətinin yaxşılaşması  "
    ]
  },
 
  {
    "question": "Radioterapevtik interval nədir?  ",
    "answers": [
      "Şiş toxuması ilə onu əhatə edən normal toxumanın radiohəssaslığı arasında olan fərq  ",
      "Şiş toxuması ilə qırmızı sümük iliyinin radiohəssaslığı arasında olan fərq  ",
      "normal orqan və toxumalar arasındakı həssaslıq fərqi  ",
      "Şiş toxuması ilə beyin toxumasının radiohəssaslığı arasında olan fərq  ",
      "Şiş toxuması ilə dərinin radiohəssaslığı arasında olan fərq  "
    ]
  },
  {
    "question": "Dinamiki distansion şüa müalicəsi nədir?  ",
    "answers": [
      "Şüa mənbəyi müalicə zamanı hərəkət edir  ",
      "Müalicə zamanı xəstə hərəkət edir  ",
      "Şüa mənbəyi toxumadaxili yeridilir  ",
      "Seans zamanı xəstə aktiv palatada saxlanılır  ",
      "Şüa mənbəyi müalicə zamanı hərəkətsiz qalır  "
    ]
  },
  {
    "question": "Qamma-terapevtik cihazın şüa mənbəyi hansı radioizotopdur?   ",
    "answers": [
      "Co60   ",
      "P32  ",
      "Au198  ",
      "İr192  ",
      "Cf252  "
    ]
  },
  {
    "question": "Distansion qamma terapiyada şüalanma mənbəyi harada yerləşir?  ",
    "answers": [
      "Cihazın başlıq hissəsində  ",
      "Xəstənin dərisi üzərində  ",
      "Boşluq daxilində  ",
      "Ştativdə   11   ",
      "Toxuma daxilində  "
    ]
  },
  {
    "question": "Şüa terapiyasında istifadə olunan sərt rentgen şüaları:  ",
    "answers": [
      "150-250 Kv  ",
      "310 Kv  ",
      "400 Kv  ",
      "10-20 Kv  ",
      "300-350 Kv  "
    ]
  },
  
  {
    "question": "Hansı müalicə növü zamanı xəstə mütləq aktiv palatada saxlanılmalıdır?  ",
    "answers": [
      "Kontakt şüa müalicəsi  ",
      "Cyber-knife   ",
      "Distansion qammaterapiya  ",
      "Protonoterapiya  ",
      "Distansion rentgenoterapiya   12   "
    ]
  },
  {
    "question": "Hansı xəstəlikdə radionuklid terapiya aparmaq olar?  ",
    "answers": [
      "Dəri xərçəngi  ",
      "Osteomielit  ",
      "Mədə xərçəngi  ",
      "Radikulit  ",
      "Qalxanvari vəzin xərçəngi  "
    ]
  },
  {
    "question": "Ağciyər xərçənginin hansı formaları var?  ",
    "answers": [
      "Mərkəzi, periferik və atipik  ",
      "Iri və kiçik  ",
      "Ilkin və gecikmiş  ",
      "Sərbəst və qarışıq  ",
      "Düz və qeyri-düz  "
    ]
  },
  
  {
    "question": "Şişin ölçüsünü əks etdirən simvol hansıdır?  ",
    "answers": [
      "N  ",
      "P  ",
      "L  ",
      "M  ",
      "T  "
    ]
  },
  {
    "question": "Regionar limfa düyününü əks etdirən simvol hansıdır?  ",
    "answers": [
      "N  ",
      "L  ",
      "P  ",
      "T  ",
      "M  "
    ]
  },
 
  {
    "question": "Qida borusu xərçənginin braxiterpiyası necə aparılır? (109)  ",
    "answers": [
      "2-4 fraksiya, 7-10 gündən bir, hər seans 7 Qr  ",
      "2-4 fraksiya, 5 gündən bir, hər seans 5 Qr   ",
      "klassik üsulla cəmi doza 45 Qr-ə qədər  ",
      "BOD-2 Qr, COD-70 Qr, hər gün  ",
      "10 fraksiya, 7 gündən bir, hər seans 7 Qr  "
    ]
  },
  {
    "question": "Yerli şüa zədələnməsi hansıdır?  ",
    "answers": [
      "şüa xorası  ",
      "Anafilaktik şok  ",
      "Portal hipertenziya  ",
      "Allergiya  ",
      "Hiperqlikemik koma  "
    ]
  },
  {
    "question": "Şüa terapiyasında hansı şüalardan istifadə olunur?  ",
    "answers": [
      "yalnız ionlaşdırıcı  ",
      "yalnız yüksəktezlikli ultrasəs dalğaları  ",
      "yalnız lazer şüaları  ",
      "həm ionlaşdırıcı, həm qeyri-ionlaşdırıcı  ",
      "yalnız ionlaşdırıcı olmayan  "
    ]
  },
  {
    "question": "M. Sklodovskaya və P. Kürinin uran filizindən əldə etdikləri yeni element hansıdır?  ",
    "answers": [
      "Radium  ",
      "Cobalt  ",
      "Qurğuşun  ",
      "Radiaktiv yod  ",
      "Radiaktiv qızıl   "
    ]
  },
  {
    "question": "Orqanotropluq nədir?  ",
    "answers": [
      "radionuklidin bir üzv tərəfindən seçimli toplanması  ",
      "radionuklidin orqanizmdən xaric olmaması  ",
      "radionuklidin orqanik maddədən ibarət olması  ",
      "radionuklidin subtropik iqlim şəraitində alınması  ",
      "radionuklidin orqanların kənarlarında toplanması  "
    ]
  },
  {
    "question": "İonlaşdırıcı şüaların zərərli təsirindən qorunma tədbirləri hansılardır?  ",
    "answers": [
      "Ekran, zaman, məsafə ilə qorunma  ",
      "Vaxta qənaət etmək, immun sistemi qüvvətləndirmək  ",
      "Eynək, önlük, baxil, xalat   14   ",
      "Şüalanmadan sonra açıq havada olmaq  ",
      "Ekranlaşdırma, vaxtında yemək, məsafələri qət etmək  "
    ]
  },
  {
    "question": "Berqonye – Tribondo qanununa görə hansı hüceyrələr şüaya həssasdır?  ",
    "answers": [
      "sürətlə bölünən və differensasiyası aşağı olan   ",
      "yalnız bölünməyən hüceyrələr  ",
      "bölünməyən və differensasiysı yüksək olan hüceyrələr  ",
      "oksigensiz və bğlünməyən hüceyrələr  ",
      "zəif bölünən və differensasiyası yüksək olan hüceyrələr  "
    ]
  },
  {
    "question": "İnsanlarda növdaxili həssaslıq nədən asılıdır? ",
    "answers": [
      "yaşdan, cinsdən, dərinin rəngindən  ",
      "həssaslığından, cinsindən  ",
      "yaşından, təhsilindən, cinsindən  ",
      "cinsindən, xasiyyətindən  ",
      "yaşadığı yerdən, yaşından  "
    ]
  },
  {
    "question": "Fotoeffekt, Kompton effekt və elektron-pozitron cütlüklərin əmələ gəlməsi hansı şüaların  təsirindən yaranır?  ",
    "answers": [
      "Foton şüaların təsirindən  ",
      "Radio və lazer dalğaların təsirindən  ",
      "Kvant təbiətli və ultrasəs dalğaların təsirindən  ",
      "Korpuskulyar şüaların təsirindən  ",
      "Həm kvant, həm korpuskulyar şüaların təsirindən  "
    ]
  },
  {
    "question": "İonlaşdırıcı şüaların bioloji obyektə təsiri:  ",
    "answers": [
      "Düz və dolayı  ",
      "Dolayı və dərhal  ",
      "qıcıqlandırıcı  ",
      "sürətli və ləng  ",
      "Düz və gecikmiş  "
    ]
  },
  {
    "question": "İzodoz xəritənin fərqli dərinlikdən keçən əyrilərinin üzərindəki rəqəm nəyi göstərir?  ",
    "answers": [
      "Bu əyrinin hər nöqtəsinə çatan enerjinin faizini göstərir.  ",
      "Patoloji prosesin ölçülərini göstərir.  ",
      "Həmin nöqtədə yerləşən prosesin həcmini göstərir  ",
      "Həmin nöqtəyə çatmayan enerjini göstərir.  ",
      "Bu əyrinin bucağını göstərir.  "
    ]
  },
  {
    "question": "anatomo-topoqrafik xəritəyə patoloji ocaq əlavə olunarsa, bu nə adlanacaq?  ",
    "answers": [
      "Kliniki topoqrafik xəritə  ",
      "Fərdi şüa müalicəsi xəritəsi  ",
      "Şüalanmanın təcrübi xəritəsi  ",
      "Kritik terapevtik xəritə   15   ",
      "Kollegial toplanmış xəritə  "
    ]
  },
  {
    "question": "Radioaktiv şüanın düz təsiri dedikdə nə başa düşürsünüz?  ",
    "answers": [
      "enerji \"hədəf\" hüceyrə tərəfindən udulur  ",
      "enerji ancaq zülallar tərəfindən udulur  ",
      "enerji ancaq sağlam toxumalar tərəfindən udulur  ",
      "enerji ancaq lipidlər tərəfindən udulur  ",
      "enerji ancaq su molekulları tərəfindən udulur  "
    ]
  },
  {
    "question": "İonlaşdırıcı şüanın törətdiyi dolayı təsir nədir?  ",
    "answers": [
      "şüalanan sahədə olan su molekullarının yaratdığı dəyişiklik  ",
      "ancaq lipidlərin şüalanması zamanı yaranan dəyişiklik  ",
      "su olmayan mühitdə baş verən hadisə  ",
      "ancaq zülalların şüalanması zamanı yaranan dəyişiklik  ",
      "enerjinin \"hədəf\" hüceyrə tərəfindən udulması  "
    ]
  },
  {
    "question": "Radiomodifikatorların növləri hansılardır?  ",
    "answers": [
      "Protektorlar və sensibilizatorlar  ",
      "süni və təbii modifikatorlar  ",
      "oksigen və carbon  ",
      "Sensibilizatorlar  ",
      "Protektorlar   "
    ]
  },
  {
    "question": "Hansı element universal modifikator adlanır?  ",
    "answers": [
      "Oksigen  ",
      "Radioaktiv yod  ",
      "Aluminium  ",
      "Radioaktiv qızıl  ",
      "Hidrogen  "
    ]
  },
  {
    "question": "Oksigenin miqdarının çox olması radiohəssaslığa necə təsir edir?  ",
    "answers": [
      "artırır  ",
      "həssaslıq oksigenin miqdarından asılı deyil  ",
      "əvvəl azaldır, sonra artırır  ",
      "dəyişmir  ",
      "azaldır  "
    ]
  },
  {
    "question": "Şüaya həssas olan sistemi göstərin:  ",
    "answers": [
      "Qanyaradıcı   16   ",
      "Qığırdaq  ",
      "Sinir  ",
      "Sümük  ",
      "Əzələ  "
    ]
  },
  {
    "question": "Temperaturun artması radiohəssaslığa necə təsir edir?  ",
    "answers": [
      "artırır  ",
      "həssaslıq temperaturdan asılı deyil  ",
      "əvvəl azaldır, sonra artırır  ",
      "dəyişmir  ",
      "azaldır  "
    ]
  },
 
  {
    "question": "Şüaya davamlı sistemi göstər:  ",
    "answers": [
      "Mərkəzi sinir sistemi  ",
      "Cinsiyyət  ",
      "Dəri və selikli qişalar  ",
      "Qanyaradıcı sistem  ",
      "Mədə-bağırsaq sistemi  "
    ]
  },
  {
    "question": "Distansion qamma-terapevtik cihazın şüa mənbəyi hansıdır?   ",
    "answers": [
      "Co60  ",
      "İr192  ",
      "Ru186  ",
      "Ac232  ",
      "U238  "
    ]
  },
  {
    "question": "Şüa terapiyasının mərhələləri hansılardır?   ",
    "answers": [
      "Hazırlıq, şüalanma, şüalanmadan sonrakı dəyişikliklərin müalicəsi  ",
      "Dozimetriya və topometriya  ",
      "Hazırlıq və reaksiya və fəsadların profilaktikası  ",
      "Şüalanma, reaksiya və fəsadların müalicəsi və profilaktikası  ",
      "Hazırlıq və şüalanma  "
    ]
  },
  {
    "question": "Hazırlıq mərhələsində aparılan önəmli işlər:  ",
    "answers": [
      "kliniki topometriya və dozimetrik planlaşdırılma  ",
      "Şişin dərinliyinin və növünün təyini  ",
      "Şüanın düşmə bucağının təyini  ",
      "Şişin ətraf toxumalara sirayətinin təyini  ",
      "Şişin proyüksiyasının dəri səthində qeyd olunması  "
    ]
  },
  {
    "question": "Xəstə hansı müalicə zamanı ikincili şüa mənbəyinə çevrilir?  ",
    "answers": [
      "Daxili şüalanma zamanı  ",
      "Xarici şüalanma zamanı  ",
      "Distant müalicə zamanı  ",
      "Kimyaterapiya zamanı  ",
      "Kompleks müalicə zamanı  "
    ]
  },

  {
    "question": "Hansı proseslərin müalicəsində istifadə olunan ümumi doza 40-90 Qr-dir?  ",
    "answers": [
      "Bədxassəli şişlər  ",
      "Ürək çatışmazlığı  ",
      "Beyin ödemi  ",
      "Qeyri-şiş mənşəli xəstəliklər  ",
      "Yemək borusunun atreziyası  "
    ]
  },
  {
    "question": "Hipertermiya seansı zamanı hüceyrələr hansı bölünmə fazasında ləngiyir?   ",
    "answers": [
      "S-sintez fazası  ",
      "M-mitoz faza  ",
      "G2 postsintetik faza  ",
      "G1 presintetik faza  ",
      "G0 fazası  "
    ]
  },
  {
    "question": "Şüalanmanın optimal miqdarı nədir?  ",
    "answers": [
      "95% halda radikal nəticə və 5% halda zədələnmə yaradan şüanın miqdarı  ",
      "50% halda radikal nəticə və 50% halda zədələnmə yaradan şüanın miqdarı  ",
      "75% halda radikal nəticə və 25% halda zədələnmə yaradan şüanın miqdarı  ",
      ") 5% halda müsbət nəticə və 95% halda fəsad yaradan şüanın miqdarı  ",
      "Fəsad törətməyən şüanın miqdarı  "
    ]
  },
  {
    "question": "Şüa müalicəsində istifadə olunan hiperqlikemiyanın məqsədi  ",
    "answers": [
      "Şiş hüceyrəsinə toplanan şəkərin parçalanması nəticəsində orada süd turşusunun əmələ gəlməsi  ",
      "Qlükozanın sintez fazasını sürətləndirməsi  ",
      "Şəkərin qələviyə çevrilməsi  ",
      "Şişdə toplanan şəkərin sulfat turşusuna çevrilməsi  ",
      "Qlükozanın presintetik fazanı ləngitməsi  "
    ]
  },
  {
    "question": "Hiperqlikmiya zamanı hüceyrələrin çox hissəsi hansı fazada ləngiyir? ",
    "answers": [
      "S-sintez fazası  ",
      "G2 postsintetik faza  ",
      "G0 fazası  ",
      "M-mitoz faza  ",
      "G1 presintetik faza   18   "
    ]
  },
  {
    "question": "Şüalanma ritmi nədir?   ",
    "answers": [
      "Fraksiyaların ardıcıllığı  ",
      "Fraksiyaların cəmi   ",
      "müalicəvi doza  ",
      "Fraksiyaların bölünməsi  ",
      "birdəfəlik doza  "
    ]
  },
  {
    "question": "Nə ücün dəri xəstəliklərinin müalicəsində az enerjili rentgen şüalarından istifadə  olunur?  ",
    "answers": [
      "Şüalanma enerjisinin 100%-i dəri səthinə düşür  ",
      "Şüalanma enerjisinin 50%-i dəri səthində olur  ",
      "Şüalanma enerjisinin 40%-i dəri səthində olur  ",
      "Şüalanma enerjisinin 80%-i dəri səthində olur  ",
      "Şüalanma enerjisinin 10%-i dəri səthinə düşür  "
    ]
  },
  {
    "question": "Şüa terapiyasında hansı fraksiyalar istifadə olunur?  ",
    "answers": [
      "Klassik, orta, iri  ",
      "Hiperfraksion, birdəfəlik  ",
      "Bölünmüş, kiçik, birdəfəlik  ",
      "cəmlənmiş, kiçik, birdəfəlik  ",
      "İri, orta, hipofraksion  "
    ]
  },
  {
    "question": "Şüalanmanı virtual modelləşdirmək üçün istifadə olunan cihaz:   ",
    "answers": [
      "KT-simulyator  ",
      "Qamma-met  ",
      "MRT  ",
      "Mobetron  ",
      "Teragam  "
    ]
  },
  {
    "question": "Müasir 3D konform şüalanmanın üstün cəhəti:  ",
    "answers": [
      "patoloji toxumada maksimal və sağlam toxumalarda minimal zədələnmənin alınması   ",
      "bu metodla düzbucaqlı sahələr yaradılaraq şüalanma aparılır  ",
      "Bu metod ilə böyük həcmləri əhatə etmək mümkündür  ",
      "Metodika maddi baxımdan qənaətlidir  ",
      "Yeni metodika ilə şüalandırma az vaxt tələb edir  "
    ]
  },
  {
    "question": "Ölçüsündən asılı olmayaraq şiş döş qəfəsinə, diafraqmaya, plevraya, perikarda keçib.  Bu təsvir ağciyər xərçənginin hansı mərhələsinə uyğundur?  ",
    "answers": [
      "III (T3)  ",
      "I-II (T 1-2)  ",
      "II (T2)  ",
      "I (T1)  ",
      "IV (T4)  "
    ]
  },
  {
    "question": "Qırtlaq xərçənginin əmələ gəlmə riskini artıran faktorlar:  ",
    "answers": [
      "Kimyəvi və radioaktiv maddələrin tozu olan iş şəraiti, alkoqolun və siqaretin istifadəsi,  papillomalar  ",
      "Ağız boşluğu xəstəlikləri, dişlərin kariesi, hemofiliya  ",
      "Çəki defisiti, xroniki yorğunluq  ",
      "Ağciyər vərəmi, pnevmoniya, ateroskleroz  ",
      "Piylənmə, siqaretçəkmə, anemiya   19   "
    ]
  },
  {
    "question": "Qida borusunun xərçəngi zamanı ən çox rast gələn simptom hansıdır?  ",
    "answers": [
      "Disfaqiya  ",
      "Displaziya  ",
      "Disharmoniya  ",
      "Disfunksiya  ",
      "Disfoniya  "
    ]
  },
  {
    "question": "Qida borusunun xərçənginin braxiterapiyasında hansı şüa mənbəyindən istifadə  olunur?  ",
    "answers": [
      "İr192  ",
      "Cs137   ",
      "İ131   ",
      "Tc99m   ",
      "Co60  "
    ]
  },

  {
    "question": "Xəstə, həftədə 5 dəfə, hər gün 2 Qr dozada şüalanarsa, bu hansı şüalanma rejimidir?  ",
    "answers": [
      "klassik  ",
      "iri  ",
      "intensiv  ",
      "dinamiki  ",
      "qənaətli  "
    ]
  },
  {
    "question": "İntraoperasion şüalanma necə aparılır?  ",
    "answers": [
      "Cərrah əməliyyat zamanı açıq şüalanma sahəsi yaradır və şişə bir dəfəyə 20 Qr şüa yönəldilir.   ",
      "Cərrah əməliyyat zamanı açıq şüalanma sahəsi yaradır və şişə 50 Qr şüa yönəldilir.  ",
      "Cərrah əməliyyat zamanı açıq şüalanma sahəsi yaradır və şişə 1-2 Qr şüa yönəldilir.  ",
      "Əməliyyatdan öncə xəstə lokal şüalanır.  ",
      "Əməliyyat zamanı patoloji ocağa şüa mənbələri yeridilir.  "
    ]
  },
  {
    "question": "Konform şüalanma nə deməkdir?  ",
    "answers": [
      "Çoxləçəkli kollimatorlarla mürəkkəb fiqurlu şüalanma sahələrinin yaradılması  ",
      "Braxiterapiyanın bir növüdür  ",
      "Distansion qamma-terapevtik aparatlarda bir neçə sahənin eyni zamanda şüalandırılması  ",
      "Şüalanma zamanı xəstəyə komfortlu şəraitin yaradılması  ",
      "Sadə kollimatorlarla təchiz olunan cihazda sadə formalı sahələrin əldə olunması  "
    ]
  },
  {
    "question": "GTV nədir?  ",
    "answers": [
      "Şişin böyük, görünən həcmidir.  ",
      "hədəfin klinik həcmidir  ",
      "Ultrasəs müayinəsi əsasında təyin edilən həcmdir.  ",
      "Kontraslı müayinə əsasında təyin edilən həcmdir.  ",
      "planlaşdırılan həcmdir  "
    ]
  },
  {
    "question": "CTV –nədir?  ",
    "answers": [
      "Hədəfin klinik həcmi və subklinik yayılma zonalarının cəmidir  ",
      "planlaşdırılan həcmdir  ",
      "Həssas toxumaların sərhədləri daxil olmaqla təyin edilən həcmdir.  ",
      "Şişin böyük, görünən həcmidir.  ",
      "Ultrasəs müayinəsi əsasında təyin edilən həcmdir.  "
    ]
  },
  {
    "question": "Enerjisi 6-20 MeV olan elektron dəstəsinin nüfuzetmə dərinliyini göstərin:   ",
    "answers": [
      "10-20 sm   21   ",
      "4-6 sm.   ",
      "0,4-0,6 mm.  ",
      "46-60 sm.  ",
      "40-60 sm  "
    ]
  },
  {
    "question": "Distansion şüa müalicəsi hansı rejimlərdə aparılır?  ",
    "answers": [
      "Statik və dinamik  ",
      "Fərdi və ümumi.  ",
      "Statik və kontakt.  ",
      "Kontakt və dinamiki.  ",
      "Stasionar və ambulator  "
    ]
  },
  {
    "question": "Statik distansion şüalanma növləri.  ",
    "answers": [
      "Birsahəli və çoxsahəli.  ",
      "Yalniz rotasion  ",
      "Konverqent və bir sahəli.  ",
      "Kontakt və çoxsahəli.  ",
      "Retasion, sektorlu.  "
    ]
  },
  {
    "question": "Bir sahəli distansion şüalanma nə zaman tətbiq olunur?  ",
    "answers": [
      "Səthdə yerləşən və həssaslığı dərinin həssaslığına bərabər olan proseslərdə  ",
      "Ancaq iltihabi proseslərdə  ",
      "Səthdə yerləşən radiorezistent şişlərdə  ",
      "Radiohəssas, iri ölçülü dırində yerləşən proseslərdə  ",
      "Radiorezistent, kiçik ölçülü dərində yerləşən proseslərdə  "
    ]
  },
  {
    "question": "Çoxsahəli distansion şüa terapiyasının istifadəsinə göstəriş hansıdır?   ",
    "answers": [
      "Dərin və radiorezistent şişlər  ",
      "Yalnız iltihabi proseslər  ",
      "Mürəkkəb formalı patoloji ocaq  ",
      "Səthi və radiorezistent şişləri  ",
      "Dərin və radiohəssas şişlər  "
    ]
  },
  {
    "question": "Radionuklidlərin seçimli toplanmasının əsas tələbi?   ",
    "answers": [
      "Elementin orqanotropluğu  ",
      "Elementin bədəndən tam xaric olması  ",
      "Elementin parçalanma müddətinin uzun olması  ",
      "Elementin flüoressensiya qabiliyyəti  ",
      "Elementin nüfuz etmə qabiliyyəti  "
    ]
  },
  {
    "question": "Şüa terapiyası məqsədinə görə:  ",
    "answers": [
      "Radikal, palliativ, simptomatik ola bilər  ",
      "adyuvant, dinamiki ola bilər  ",
      "Dinamiki, palliativ, bölünmüş ola bilər  ",
      "Kontakt, distansion, rotasion ola bilər  ",
      "Statik, distansion, irifraksiyalı ola bilər  "
    ]
  },
  
  {
    "question": "Hansı üzvün bədxassəli şişi, o üzv üçün regionar olan bronxopulmonal, divararalığı,  traxeobronxeal, paratraxeal limfa düyünlərə sürətlə yayılar?   ",
    "answers": [
      "Ağciyər xərçəngi  ",
      "Uşaqlıq boynu xərçəngi  ",
      "Qida borusu xərçəngi  ",
      "Çənə sümüyünün xərçəngi  ",
      "Düz bağırsaq xərçəngi  "
    ]
  },
  {
    "question": "Kontakt şüa müalicəsinə aid olan üsulu göstərin:  ",
    "answers": [
      "boşluqdaxili  ",
      "çoxsaylı  ",
      "birdəfəlik  ",
      "sektoral  ",
      "konvergent  "
    ]
  },
  {
    "question": "Qırtlaq xərçəngi 98% halda hansı histoloji quruluşa malik olur?  ",
    "answers": [
      "Yastıhüceyrəli xərçəng  ",
      "adenokarsinoma  ",
      "Sarkoma  ",
      "Vəzli xərçəng  ",
      "Bazalhüceyrəli xərçəng  "
    ]
  },
  {
    "question": "Qırtlağın hansı sahəsi həm radiohəssas, həm də aqressiv gedişatlıdır?   ",
    "answers": [
      "Vestibulyar sahə  ",
      "Bağaltı hissə  ",
      "Səs telləri ilə bağaltı sahələrin sərhədi  ",
      "Səs telləri nahiyəsi  ",
      "Hər 3 sahə  "
    ]
  },

  {
    "question": "Şüa terapiyasında β- şüa mənbəyi kimi istifadə olunan elementləri göstərin:  ",
    "answers": [
      "P32, Y90, Sr89  ",
      "P 31, Co 60, Tc99  ",
      "N14, Cs 137, Co 60  ",
      "Pl 98, İn 111, Fe 59  ",
      "Co 60, Cf 252, İ131  "
    ]
  },
  {
    "question": "Müsbət yüklü hissəcikləri qeyd edin: (32,33)  ",
    "answers": [
      "α-hissəcik, proton  ",
      "α-şüa, deyton, foton  ",
      "rentgen şüa, π - mezon  ",
      "neytron, pozitron, γ – şüa   24   ",
      "elektronlar, β-hissəcik, γ-şüa  "
    ]
  },
  {
    "question": "50 KeV enerjili fotonlar hansı effekti yaradır?  ",
    "answers": [
      "Fotoeffekt  ",
      "Protoneffekt  ",
      "Annihilyasiya  ",
      "Fotoblok  ",
      "Kompton effekt  "
    ]
  },
  {
    "question": "125 KeV enerjili fotonlar hansı effekti yaradır?  ",
    "answers": [
      "Kompton effekti  ",
      "Fotoeffekt   ",
      "Annihilyasiya  ",
      "Proton effekti  ",
      "Komfort effekti  "
    ]
  },
  {
    "question": "Annihilyasiyalı şüalanma yaradan fotonun enerjisini göstərin:   ",
    "answers": [
      "1,02 MeV-dan çox  ",
      "100 eV  ",
      "1 MeV-dan az  ",
      "10 KeV  ",
      "0,1 MeV az  "
    ]
  },
  {
    "question": "Hüceyrələrin differensasiya dərəcəsi və şüaya həssaslıq arasındakı asılılıq:  ",
    "answers": [
      "Differensasiya dərəcəsi artdıqca şüaya həssaslıq azalır  ",
      "Differensasiya dərəcəsi ilə şüaya həssaslıq arasında asılılıq yoxdur  ",
      "Differensasiya dərəcəsi artdıqca şüaya həssaslıq artır  ",
      "Yastı hüceyrəli şişlərin şüaya həssaslığı differensasiyadan asılı deyil  ",
      "Yüksək differensasiyalı hüceyrələr ancaq rentgen şüalarına həssasdır  "
    ]
  },
  {
    "question": "Hansı şişlər şüa müalicəsi üçün əlverişlidir?  ",
    "answers": [
      "radiohəssas  ",
      "ancaq qadınlarda radiohəssaslıq vacibdir  ",
      "patoloji prosesin mərkəzi rezistent olsa müalicə uğurlu olar  ",
      "radiodavamlı  ",
      "bu göstəricilər şüa terapiyasına təsir etmir  "
    ]
  },
  {
    "question": "Səthi proseslərin müalicəsində dəri applikatoru kimi istifadə olunan şüa mənbəyi  hansıdır?  ",
    "answers": [
      "Co60  ",
      "İ131  ",
      "Cs137  ",
      "Au198  ",
      "P32   25   "
    ]
  },
  {
    "question": "Hansı şua mualicəsi üsulunda dəri fokus məsafəsi 5-35 sm dir?  ",
    "answers": [
      "Qısa fokuslu  ",
      "Aplikasiyon  ",
      "Braxiterapiya  ",
      "Toxumadaxili  ",
      "Uzun fokuslu  "
    ]
  },
  {
    "question": "Hansı şua mualicəsi üsulunda dəri fokus məsafəsi 35-100 sm dir?  ",
    "answers": [
      "Uzun fokuslu  ",
      "Braxiterapiya  ",
      "Aplikasiyon  ",
      "Toxumadaxili  ",
      "Qısa fokuslu  "
    ]
  },
  {
    "question": "Distansion şüalanma zamanı qurğuşun bloklar nə üçün istifadə olunur?  ",
    "answers": [
      "ətraf toxumaları qorumaq üçün  ",
      "Müalicə seansının vaxtını qısaltmaq üçün  ",
      "Şisin həssaslığını artırmaq üçün  ",
      "Şua dozasını artırmaq üçün  ",
      "Xəstənin vəziyyətini yaxşılaşdırmaq üçün  "
    ]
  },
  {
    "question": "Bazaleomaların müalicəsində ən çox istifadə olunan şüa terapiyası növü hansıdır?  ",
    "answers": [
      "Qısa fokuslu rentgen terapiya  ",
      "Boşluqdaxili şüa müalicəsi  ",
      "Protonterapiya  ",
      "Uzun fokuslu rentgen terapiya  ",
      "Uzun fokuslu qamma terapiya  "
    ]
  },
  {
    "question": "Ağız boşluğu xərçəngində ən tez zədələnən hansı limfatik düyünlərdir?  ",
    "answers": [
      "çənəaltı  ",
      "körpücüküstü  ",
      "körpücükaltı  ",
      "qasıq  ",
      "qoltuqaltı  "
    ]
  },
  {
    "question": "Alt dodaq xərçənginin erkən mərhələlərində hansı şüa terapiyası üsullarından istifadə  olunur?  ",
    "answers": [
      "Qısa fokuslu rentgenterapiya, elektron dəstəli braxiterapiya  ",
      "Neytron tutucu terapiya və braxiterapiya  ",
      "Boşluqdaxili braxiterapiya və protonterapiya  ",
      "Distansion qammaterapiya və Gamma-knife  ",
      "Uzun fokuslu rentgenterapiya və Cyber-knife   26   "
    ]
  },
  {
    "question": "Üst çənə şişlərinin şüa terapiyasında ən çox hansı şüa mənbələrindən istifadə oulnur?  ",
    "answers": [
      "γ – şüalar  ",
      "adronlar  ",
      "protonlar  ",
      "pozitronlar  ",
      "α-hissəciklər  "
    ]
  },
  {
    "question": "Alt dodaq xərçənginin kontakt qamma terapiyasında COD nə qədər olmalıdır?  ",
    "answers": [
      "50-60-65 Qr  ",
      "15-20-25 Qr  ",
      "10-20-30 Qr  ",
      "1-2 Qr  ",
      "5-10-15 Qr  "
    ]
  },
  {
    "question": "Burun-udlaq şişlərinin müalicəsində limfoepitelial şişlər hansı dozada şüalandırılır?  ",
    "answers": [
      "COD 60 Qr  ",
      "COD 110 Qr  ",
      "COD 10 Qr  ",
      "COD 30 Qr  ",
      "COD 100 Qr  "
    ]
  },
  {
    "question": "Ağciyər xərçənginin hansı histoloji forması şüaya daha həssasdır?  ",
    "answers": [
      "kiçikhüceyrəli   ",
      "yastıhüceyrəli  ",
      "irihüceyrəli  ",
      "bütün ağciyər şişlərinin həssaslığı eynidir  ",
      "adenokarsinoma   "
    ]
  },
  {
    "question": "Toxumadaxili şüa müalicəsində istifadə olunan radioizotoplar:  ",
    "answers": [
      "Co 60, Cs 137, Ta 182, İr 192  ",
      "U 238, Ac 225, H 1  ",
      "P 32, P 31, J 131  ",
      "Y 90, J 131, Au 198, Cf 252  ",
      "Au 198, P 31, J 131  "
    ]
  },
  {
    "question": "Hərəkətli qoruyucu vasitələr hansılardır?  ",
    "answers": [
      "şirmalar və konteynerlər  ",
      "arakəsmələr və sütunlar  ",
      "seyflər və çarpayılar  ",
      "divarlar və tavanlar  ",
      "qapılar və pəncərələr  "
    ]
  },
  {
    "question": "Hərəkətsiz qoruyucu vasitələri göstərin:  ",
    "answers": [
      "divarlar, daş arakəsmələr  ",
      "konteynerlər, şirmalar   27   ",
      "seyflər, şirmalar  ",
      "əlcəklər, qapılar  ",
      "önlüklər, eynəklər  "
    ]
  },
  {
    "question": "fərdi ekranlar hansılardır?  ",
    "answers": [
      "önlüklər və əlcəklər  ",
      "seyflər, qapılar  ",
      "arakəsmələr, seyflər  ",
      "divarlar, arakəsmələr  ",
      "qapılar, pəncərələr  "
    ]
  },
  
  {
    "question": "Bədxassəli şişlərin müalicəsində istifadə olunan şüa terapiyasının əsas məqsədi :  ",
    "answers": [
      "letal zədələnmə əldə etmək  ",
      "prosesi sürətləndirmək  ",
      "mübadilə prosesini sürətləndirmək  ",
      "subletal zədələnmə əldə etmək  ",
      "trofikanı bərpa etmək  "
    ]
  },
  {
    "question": "Distansion qamma-terapevtik cihazın şüa mənbəyi hansı radioaktiv elementlərdir? ",
    "answers": [
      "Co60, Cs137  ",
      "İr 192, Cf 252  ",
      "Ac225 Au 198  ",
      "Sr 89, J131  ",
      "U 238, Rn16  "
    ]
  },
  {
    "question": "Rentgenterapevtik cihazın tərkibində olan süzgəclərin rolu :   səh 148 28   ",
    "answers": [
      "Az nüfuzlu enerji kvantlarının qarşısını almaq  ",
      "Az nüfuzlu korpuskulyar şüalanmanın qarşısını almaq  ",
      "Şüaları səpələmək  ",
      "Rentgen şüalanmanın nüfuzetmə qabiliyyətini zəiflətmək   ",
      "Rentgen şüalanmanın nüfuzetmə qabiliyyətini gücləndirmək   "
    ]
  },
  {
    "question": "Rentgenterapevtik cihazın tərkibində olan süzgəclər:  ",
    "answers": [
      "Alüminium, mis  ",
      "Molibden, gümüş  ",
      "Platin, mis  ",
      "Qızıl, gümüş  ",
      "Dəmir, platin  "
    ]
  },
  {
    "question": "Burun-udlaq nahiyəsi retikulosarkomalarında istifadə olunan şüalanma dozası:  ",
    "answers": [
      "COD 70 Qr  ",
      "COD 40 Qr  ",
      "COD 120 Qr  ",
      "COD 10 Qr  ",
      "COD 15 Qr  "
    ]
  },
 
  {
    "question": "Hansı məqsədlə əməliyyatdan sonra şüa terapiyası aparılır?  ",
    "answers": [
      "əməliyyatın radikallığını artırmaq, metastaz və residivlərin profilaktikasını aparmaq   ",
      "Müalicənin radikallığını təmin etmək, şişin böyüməsini ləngitmək  ",
      "şişin həcmini kiçiltmək  ",
      "Metastazların profilaktikası, ətraf toxuma zədələnməsini aradan qaldırmaq  ",
      "Residivlərin profilaktikası, ətraf toxuma zədələnməsini aradan qaldırmaq  "
    ]
  },
  {
    "question": "Braxiterapiya nədir?   ",
    "answers": [
      "Kiçik məsafədən aparılan müalicə  ",
      "aplikasion müalicə  ",
      "bo.luqdaxili müalicə  ",
      "uzaq məsafədən aparılan müalicə  ",
      "Distansion metod  "
    ]
  },
  {
    "question": "“Aktiv” xəstə hansıdır?  ",
    "answers": [
      "bədəninə radionuklid yerləşdirilən xəstə  ",
      "Distansion müalicə alan xəstə  ",
      "Kimyəvi terapiya alan xəstə  ",
      "Kompleks müalicə alan xəstə  ",
      "bədəninə kontrast maddə yeridilən xəstə  "
    ]
  },
  
  {
    "question": "Hansı patoloji proseslərin müalicəsində şüa terapiyası tətbiq oluna bilər?  ",
    "answers": [
      "Bəd xassəli şişlərin və bir sıra qeyri-şiş xarakterli proseslərin  ",
      "Xroniki qastrit və xora  ",
      "Xoralı kolit və reflyuks  ",
      "Ürək vı böyrək çatışmazlığı  ",
      "Qaraciyərin müxtəlif piylənmə dərəcələrində  "
    ]
  },
  {
    "question": "Yüksək enerjili mənbələrin istifadəsinin üstünlüyü nədir? ",
    "answers": [
      "eyni dərinlikdə yerləşən fərqli sıxlıqlı toxumalar tərəfindən bərabər udulması  ",
      "müxtəlif dərinlikdə yerləşən toxumalar tərəfindən qeyri-bərabər udulması   ",
      "zəif dərinlik dozası   ",
      "eyni dərinlikdə yerləşən fərqli sıxlıqlı toxumalar tərəfindən qeyri-bərabər udulması   ",
      "müxtəlif dərinlikdə yerləşən toxumalar tərəfindən bərabər udulması  "
    ]
  },
  {
    "question": "Şüa müalicəsindən öncə nə üçün barokameralardan istifadə olunur? ",
    "answers": [
      "Şiş toxumasında oksigenin miqdarını artırmaq və onu daha həssas etmək üçün  ",
      "Həm şiş toxumasında, həm də ətraf toxumada oksigenin miqdarını artırmaq  ",
      "Şiş toxumasında oksigenin miqdarını azaltmaq, ətraf toxumada artırmaq  ",
      "Şiş toxumasında oksigenin miqdarını azaltmaq və onu daha həssas etmək üçün  ",
      "Şiş toxumasında oksigenin miqdarını artırmaq və onu şüaya davamlı etmək üçün  "
    ]
  },
  {
    "question": "Hipertermiya zamanı şişdə temperatur hansı dərəcəyə qədər artırılır?   ",
    "answers": [
      "41-450 C  ",
      "61-650 C  ",
      "1-50 C  ",
      "1000 C  ",
      "4-50 C  "
    ]
  },
  {
    "question": "Şiş toxumasında temperaturu artırmaq üçün nədən istifadə olunur?   ",
    "answers": [
      "Ultrasəs, yüksək tezlikli lazer dalğalarından  ",
      "Mikro- və radiodalğalardan  ",
      "Isti sudan  ",
      "Lazer və mikrodalğalardan  ",
      "Ultrasəs və radiodalğalardan  "
    ]
  },
  {
    "question": "Elektron-akseptor birləşmələri necə şüa terapiyasının təsirini gücləndirir?  ",
    "answers": [
      "oksigeni immitasiya edərək  ",
      "şiş toxumasında temperaturu artıraraq  ",
      "ətraf sağlam toxumaya selektiv toplanaraq  ",
      "qlükozanı süd turşusuna parçalayaraq   30   ",
      "karbonu immitasiya edərək  "
    ]
  },
  {
    "question": "Hipertermiya hüceyrələrin hansı bölünmə fazasını ləngidir?  ",
    "answers": [
      "S-sintez  ",
      "M-mitoz  ",
      "G2 postsintetik  ",
      "interfaza  ",
      "G1 presintetik  "
    ]
  },
  {
    "question": "Bədxassıli şişin şüaya həssaslığını artıran faktor hansıdır?  ",
    "answers": [
      "Hiperqlikemiya  ",
      "Hipoqlikemiya  ",
      "Hipoksemiya  ",
      "Hipermotor diskineziya  ",
      "Hipertoniya  "
    ]
  },
  {
    "question": "Hiperqlikemiyada hüceyrələrin çox hissəsi hansı bölünmə fazasında ləngiyir?   ",
    "answers": [
      "S-sintez  ",
      "interfaza  ",
      "G2 postsintetik  ",
      "G1 presintetik  ",
      "M-mitoz  "
    ]
  },
  {
    "question": "Dinamiki fraksiyalarla şüa müalicəsi necə aparılır?  ",
    "answers": [
      "şüa terapiyası mərhələlərə bölünərək fərqli fraksiyalar seçilir  ",
      "BOD 8 Qr, həftədə 1 dəfə  ",
      "BJD 3-3,2 Qr, həftədə 3 dəfə  ",
      "BOD 2-2,2 Qr, həftədə 3 dəfə  ",
      "BOD 1,5 Qr, həftədə 5 dəfə  "
    ]
  },
  {
    "question": "Orta və intensiv fraksiyalarda istifadə olunan gündəlik doza:   ",
    "answers": [
      "4-5 Qr  ",
      "10-20 Qr  ",
      "7-8 Qr  ",
      "2-3Qr  ",
      "5-10 Qr  "
    ]
  },
  {
    "question": "VDF nədir? (47)  ",
    "answers": [
      "Vaxt-doza-fraksiya  ",
      "Vaxt-dalğa-fraksiya  ",
      "Vaxt-doza-funksiya  ",
      "Volt-dalğa-fraksiya  ",
      "Vaxt-doza-film  "
    ]
  },
  {
    "question": "Enerjinin toxumalarda fiqurlu və ya rəqəmsal paylanmasını əks edən xəritələrə :   ",
    "answers": [
      "izodoz xəritəsi deyilir  ",
      "enerji xəritəsi deyilir  ",
      "paylanma xəritəsi deyilir  ",
      "izobar xəritəsi deyilir  ",
      "udulma xəritəsi deyilir  "
    ]
  },
  {
    "question": "Simptomatik şüa terapiyasının əsas məqsədi:  ",
    "answers": [
      "Bədxassəli proseslərə xas olan simptomların aradan qaldırılması   31   ",
      "Şişin radikal yolla kəsilib götürülməsi  ",
      "Daha radiohəssas şiş yaradılması  ",
      "Letal zədələnmə əldə etmək  ",
      "Şişin tam reqressiyasının əldə edilməsi  "
    ]
  },
  {
    "question": "Palliativ şüa terapiyasının məqsədi?  ",
    "answers": [
      "Şişin inkişafının və yayılmasının qarşısını almaq  ",
      "Şişin simptomlarının aradan qaldırılması  ",
      "Daha həssas şiş hüceyrələrinin əmələ gəlməsi  ",
      "Şişin tam reqressiyasının əldə edilməsi  ",
      "Letal zədələnmə əldə etmək  "
    ]
  },
  {
    "question": "Kombinə olunmuş şüa müalicəsi nədir?  ",
    "answers": [
      "iki əsas müalicə növünün birgə istifadəsi  ",
      "yalnız cərrahi müdaxilə  ",
      "müztəlif kimyəvi dərman preparatlarının birgə istifadəsi  ",
      "üç və daha çox müalicə üsullarının bir yerdə istifadəsi  ",
      "ancaq şüa terapiyasının müxtəlif metodlarının birgə istifadəsi  "
    ]
  },
  
  {
    "question": "Hansı şüa müalicəsini aparmaqda məqsəd şiş toxumasının ölçülərinin kiçildilməsi,  vəziyyətinin yaxşılaşdırılması və nəticədə xəstələrin yaşama müddətinin uzadılmasıdır?  ",
    "answers": [
      "Palliativ   ",
      "kompleks  ",
      "Müştərək   ",
      "kombinəolunmuş  ",
      "Radikal   "
    ]
  },
 
  {
    "question": "Xarici şüalanmadan sonra xəstənin tibb personalına göstərə biləcəyi təhlükə:  ",
    "answers": [
      "Heç bir təhlükə törətmir  ",
      "Xəstə özündən qamma şüalar xaric edir  ",
      "Xəstənin bədəni betta şüalanma verir  ",
      "Xəstə sidiklə radionuklidlər xaric edir  ",
      "Xəstənin bədənində qamma şüalanma davam edir  "
    ]
  },
  {
    "question": "Xarici şüalanmanın rotasion üsulunun mənfi cəhəti nədir? ",
    "answers": [
      "inteqral dozanın böyük olması və ümumi şüa reaksiyalarının artması  ",
      "mərkəzdə yerləşən şişin qeyri-bərabər şüalanması  ",
      "dəridə dəyişikliklərin müşahidə olunması  ",
      "inteqral dozanın azalması və yerli şüa reaksiyalarının artması  ",
      "nisbi dərinlik dozanın artması  "
    ]
  },
  {
    "question": "Hansı mənbəli distansion şüa terapiyası alan xəstə seansdan sonra ətrafdakılar üçün  təhlükəlidir?   32   ",
    "answers": [
      "Cf 252  ",
      "Rn 116  ",
      "Co 60  ",
      "J131  ",
      "Cs 137  "
    ]
  },
  {
    "question": "Radionuklid müalicənin hansı növləri var?  ",
    "answers": [
      "sistemli, şişdaxili, damardaxili  ",
      "Limfadaxili və orqandaxili  ",
      "orqandaxili, distansion  ",
      "sistemli və sistemsiz  ",
      "səthi və dərin  "
    ]
  },
  {
    "question": "Təbabətdə istifadə olunan RFP-ın yarımparçalanma müddəti nə qədər olmalıdır?  ",
    "answers": [
      "5-10 saat-5-10 gün  ",
      "5-7 ay  ",
      "0,1-0,5 dəq  ",
      "5-7 il  ",
      "1 ildən çox olmayaraq  "
    ]
  },
  {
    "question": "Radioloji şöbələrdə işləyən tibb personalının imtiyazları hansılardır?  ",
    "answers": [
      "4 iş saatı, uzadılmış məzuniyyət, erkən təqaüd (47 yaş)   ",
      "Əlavə qoruyucularla təminat.   ",
      "Pulsuz dərmanlar, minimal qida məhsulları ilə təminat.   ",
      "İş saatının həftədə 47 saata çatması, gündəlik iş saatı 6 saat   ",
      "İş saatının uzadılması, 40 yaşdan təqaüd.   "
    ]
  },
  {
    "question": "Radioaktiv maddənin aktivliyini və ya konsentrasiyasını ölçən vasitə hansıdır?  ",
    "answers": [
      "radiometr  ",
      "voltmetr  ",
      "ampermetr  ",
      "termometr  ",
      "dozimetr  "
    ]
  },
  
  {
    "question": "Bazaliomaların müalicəsində nə üçün üstünlük şüa terapiyasına verilir?   ",
    "answers": [
      "Şişin şüaya həssas olması, gözəl kosmetik nəticə  ",
      "Müalicə qısa müddətli olduğu üçün  ",
      "Qan itkisi olmadığı üçün   33   ",
      "Şüa terapiyasına üstünlük verilmir  ",
      "Müalicə çox ucuz başa gəldiyi üçün  "
    ]
  },
  {
    "question": "Hər gün 2-3 dəfə adi fraksiyalarla aparılan fraksion sxem hansıdır?  ",
    "answers": [
      "sürətlənmiş  ",
      "orta  ",
      "intensiv  ",
      "dinamiki  ",
      "klassik  "
    ]
  },
  {
    "question": "Ətraf normal toxuma ilə şiş toxuması arasındakı həssaslıq fərqi necə adlanır?  ",
    "answers": [
      "Radioterapevtik interval  ",
      "Radioizotop fərq  ",
      "Müalicə effekti  ",
      "Radiasion nəzarət  ",
      "Radionuklid interval  "
    ]
  },
  
  {
    "question": "EXP göstəricisi nəyi əks edir?  ",
    "answers": [
      "Şüa enerjisinin sirayət etdiyi bir vahid məsafəyə ötürdüyü enerjini  ",
      "hava tərəfindən udulan enerjinı  ",
      "daxili üzvlər tərəfindən udulan enerjinı  ",
      "enerjinin qeyri-bərabər paylanmasını  ",
      "bir vahid həcmə verilən enerjinin miqdarını  "
    ]
  },
  {
    "question": "İonlaşdırıcı şüanın təsirindən elementdə yaranan qığılcımları elektrik impulsuna çevirən  hansı dozimetrdir?  ",
    "answers": [
      "ssintilyasiyaedici dozimetr  ",
      "bioloji dozimetr  ",
      "yarımkeçirici dozimetr  ",
      "ionizasiyalı dozimetr   34   ",
      "fotokimyəvi dozimetr  "
    ]
  },
  {
    "question": "Tsiklik sürətləndiricilər hansılardır?  ",
    "answers": [
      "sinxrotron və sinxrotsiklotron  ",
      "R-terapevtik aparat  ",
      "nüvə reaktoru   ",
      "xətli sürətləndirici  ",
      "γ terapevtik aparat  "
    ]
  },
  {
    "question": "Ölçüsündən asılı olmayaraq şiş divararalığına, ürəyə, böyük damarlara, traxeyaya, qida  borusuna, fəqərə cisminə keçibsəŞ bu ağciyər xərçənginin hansı mərhələsidir?   ",
    "answers": [
      "T4  ",
      "T2  ",
      "T3  ",
      "T1  ",
      "T in situ  "
    ]
  },
  {
    "question": "Şüa müalicəsinin effektini artıran tədbirlər hansılardır?  ",
    "answers": [
      "Hipertermiya, hiperqlikemiya   ",
      "Hipertemiya ,hipodinamiya   ",
      "Hipoqlikemiya  ",
      "Arterial təzyiqi tənzimləmək  ",
      "hiperqlikemiya və hipoqlikemiya  "
    ]
  },
  
  {
    "question": "Üzv transplantasiyasından sonra hansı şüalanmadan istifadə olunur?(169)  ",
    "answers": [
      "total şüalanma  ",
      "iri fraksiyalı şüalanma  ",
      "split kurslu şüalanma  ",
      "lokal şüalanma  ",
      "subtotal şüalanma  "
    ]
  },
  {
    "question": "3-3,5 sm-dən kiçik beyin şişlərinin şüa müalicəsində məsləhət görülən stereotaktik şüa  terapiyası metodu hansıdır?  ",
    "answers": [
      "Gamma knife  ",
      "rentgen terapiya  ",
      "protonterapiya  ",
      "İMRT  ",
      "qamma terapiya  "
    ]
  },
  
  {
    "question": "Neytron tutucu terapiyada istifadə olunan element hansıdır?  ",
    "answers": [
      "Co60  ",
      "P31  ",
      "N14  ",
      "H1  ",
      "B10  "
    ]
  },
  {
    "question": "J 131 radionuklidi hansı radioaktiv şüalar xaric edir?   ",
    "answers": [
      "β şüalar  ",
      "protonlar  ",
      "elektronlar  ",
      "α şüalar  ",
      "γ şüalar  "
    ]
  },
  {
    "question": "J 131 radionuklidinin xaric etdiyi β şüaların toxumalarda nüfuzu nə qədərdir?  ",
    "answers": [
      "4 mm  ",
      "4 sm  ",
      "2 sm  ",
      "5 sm  ",
      "15 mm  "
    ]
  },
  {
    "question": "Hansı şüa müalicəsi zamanı xəstə ikincili şüa mənbəyinə çevrilir?   ",
    "answers": [
      "J 131 radionuklidi ilə müalicə  ",
      "qısafokuslu rentgen terapiya  ",
      "İGRT  ",
      "distansion qamma terapiya  ",
      "İMRT  "
    ]
  },
  
  {
    "question": "Qırtlaq xərçəngi vestibulyar sahə T2 göstər:  ",
    "answers": [
      "şiş dəhliz və səs telləri nahiyəsindəki anatomik sahələri tutur, səs telləri hərəkətlidir.  ",
      "qida borusu, traxeyaya sirayət var  ",
      "şiş qırtlağın sərhədlərindədir, səs telləri fiksasiya olunub.  ",
      "şiş bir anatomik sahə daxilindədir, səs telləri hərəkətlidir  ",
      "şiş dəhliz və səs telləri nahiyəsindəki anatomik sahələri tutur, səs telləri hərəkətsizdir.  "
    ]
  },
  {
    "question": "Qırtlaq xərçəngi vestibulyar sahə T3 göstər:   ",
    "answers": [
      "şiş qırtlağın sərhədlərindədir, səs telləri fiksasiya olunub.   ",
      "şiş dəhliz və səs telləri nahiyəsindəki anatomik sahələri tutur, səs telləri hərəkətlidir.  ",
      "şiş qırtlağın sərhədlərindədir, səs telləri hərəkətlidir  ",
      "qida borusu, traxeyaya sirayət var  ",
      "şiş bir anatomik sahə daxilindədir, səs telləri hərəkətlidir  "
    ]
  },
  {
    "question": "Qırtlaq xərçəngi yarıqaltı sahə T3 göstər:   ",
    "answers": [
      "şiş səs tellərini hərəkətsiz edib.   ",
      "şiş təyin olunmur   43   ",
      "qida borusu, traxeyaya sirayət var  ",
      "şiş yarıqaltı sahənin hüdudlarındadır.  ",
      "səs telləri hərəkətlidir  "
    ]
  },
  {
    "question": "Qırtlaq xərçəngi yarıqaltı sahə T2 göstər:   ",
    "answers": [
      "şiş səs tellərinin hərəkətini məhdudlaşdırıb.   ",
      "səs telləri hərəkətlidir  ",
      "şiş yarıqaltı sahənin hüdudlarındadır.  ",
      "qida borusu, traxeyaya sirayət var  ",
      "şiş təyin olunmur  "
    ]
  },
  {
    "question": "Qırtlaq xərçəngi səs yarığı sahəsi T2 göstər:  ",
    "answers": [
      "səs tellərinin hərəkəti məhduddur, şiş yanaşı sahələrə sirayət edir.  ",
      "qida borusu, traxeyaya sirayət var  ",
      "şiş təyin ounmur  ",
      "şiş qırtlaq daxilindədir, səs telləri hərəkətsizdir.  ",
      "səs telləri hərəkətlidir  "
    ]
  },
  {
    "question": "Qırtlaq xərçəngi səs yarığı sahəsi T4 göstər:  ",
    "answers": [
      "şiş qalxanabənzər qığırdağa, ağız-udlağa, boyunun yumşaq toxumalarına keçib  ",
      "şiş qırtlaq daxilindədir, səs telləri hərəkətsizdir.  ",
      "şiş təyin ounmur  ",
      "şiş səs tellərini hərəkətsiz edib.  ",
      "səs telləri hərəkətlidir  "
    ]
  },
  {
    "question": "Ağız-udlaq xərçəngi T1 göstər:  ",
    "answers": [
      "şiş 2 sm-dən kiçik   ",
      "şiş 3-7 sm  ",
      "şiş təyin olunmur  ",
      "şiş haqda məlumat yoxdur  ",
      "şiş 2-5 sm  "
    ]
  },
  {
    "question": "Ağız-udlaq xərçəngi T2 göstər:  ",
    "answers": [
      "şiş 4 sm-dən kiçik   ",
      "şiş haqda məlumat yoxdur  ",
      "şiş 3-7 sm  ",
      "şiş 2-5 sm  ",
      "şiş təyin olunmur  "
    ]
  },
  {
    "question": "Ağız-udlaq xərçəngi T3 göstər:  ",
    "answers": [
      "şiş 4 sm-dən böyük   ",
      "şiş haqda məlumat yoxdur  ",
      "şiş 3 sm-dən kiçik   44   ",
      "şiş 2-3 sm  ",
      "şiş təyin olunmur  "
    ]
  },
  {
    "question": "Ağciyər xərçənginin T2 mərhələsində şişin ölçüsünü göstər:   ",
    "answers": [
      "şiş 3-5 sm  ",
      "şiş haqda məlumat yoxdur  ",
      "şiş 25-sm-dən böyük  ",
      "şiş 1 sm-dən kiçik  ",
      "şiş təyin olunmur  "
    ]
  },
  {
    "question": "Ağciyər xərçəngi T3 mərhələsini göstər:   ",
    "answers": [
      "ölçüsündən asılı olmayaraq şiş döş qəfəsinə, diafraqmaya, plevraya, perikarda keçib.  ",
      "şiş haqda məlumat yoxdur  ",
      "preinvaziv karsinoma  ",
      "şiş təyin olunmur  ",
      "şiş 3 sm-dən kiçik  "
    ]
  },
  {
    "question": "Ağciyər xərçənginin T1 mərhələsində şişin ölçüsünü göstər:  ",
    "answers": [
      "ölçüsündən asılı olmayaraq şiş döş qəfəsinə, diafraqmaya, plevraya, perikarda keçib.  ",
      "şiş haqda məlumat yoxdur  ",
      "şiş 2 sm-dən böyükdür  ",
      "şiş təyin olunmur  ",
      "şiş 1 sm-dən kiçikdir  "
    ]
  },
  {
    "question": "Radiorezistent şişi göstər:  ",
    "answers": [
      "osteosarkoma  ",
      "semonima  ",
      "plazmositoma  ",
      "limfoma  ",
      "bazalioma  "
    ]
  },
  {
    "question": "Aşağıdakılardan hansı daha radiohəssasdır?  ",
    "answers": [
      "qanyaradıcı sistem  ",
      "qığırdaq toxuma  ",
      "əzələ toxuması  ",
      "sinir toxuması  ",
      "sümük toxuması  "
    ]
  },
  {
    "question": "Beta şüalanma mənbələri hansılardır?  ",
    "answers": [
      "Ru106, Sm153  ",
      "Ac225,Tb149  ",
      "Cf252, İr192  ",
      "Cs137, Tb149  ",
      "Co60, Ac225  "
    ]
  },
  {
    "question": "Fərdi dozimetriyada istifadə olunan vasitə hansıdır? ",
    "answers": [
      "termolüminessent dozimetr  ",
      "termometr  ",
      "yarımkeçirici dozimetr  ",
      "fiziki dozimetr   45   ",
      "bioloji dozimetr  "
    ]
  },
  {
    "question": "Az enerjili fotonlar (50-120 KeV) hansı efffekti yaradır?   ",
    "answers": [
      "fotoeffekt  ",
      "kompton effekt  ",
      "annihilyasiya  ",
      "cüt ionların əmələ gəlməsi  ",
      "oksigen effekti  "
    ]
  },
  {
    "question": "Enerjisi 120-250 KeV olan fotonlar hansı effekti yaradır?   ",
    "answers": [
      "kompton effekt  ",
      "oksigen effekti  ",
      "foton effekt  ",
      "annihilyasiya  ",
      "cüt ionlar effekti  "
    ]
  },
  {
    "question": "201 ədəd Co60 radionuklidi yerləşdirilən şüa terapevtik cihaz hansıdır?  ",
    "answers": [
      "Qamma-bıçaq  ",
      "rentgenterapevtik cihaz  ",
      "sinxrotskilotron  ",
      "xətli sürətləndirici  ",
      "Kiber- bıçaq  "
    ]
  },
  {
    "question": "Birdəfəyə 20 Qr dozasında şüalanma nə zaman verilə bilər?  ",
    "answers": [
      "intraoperasion şüalanma zamanı  ",
      "intravenoz şüa terapiyasında  ",
      "bu doza birdəfəyə verilə bilməz  ",
      "kontakt şüalanma zamanı  ",
      "distansion şüalanma zamanı  "
    ]
  },
  {
    "question": "Kişilər arasında ən çox rast gəlinən xərçəng növü hansıdır?  ",
    "answers": [
      "ağciyər xərçəngi  ",
      "sümük şişləri  ",
      "dəri xərçəngi  ",
      "mədə xərçəngi  ",
      "qida borusu xərçəngi  "
    ]
  },
  {
    "question": "Ağciyər xərçənginin əsas əmələ gəlmə səbəblərindən olan siqaretçəkmə bu xərçəngə  tutulma riskini neçə dəfə artırır?  ",
    "answers": [
      "25  ",
      "2  ",
      "7  ",
      "5  ",
      "10  "
    ]
  },
  {
    "question": "Ağciyər xərçəngində aparılan subtotal şüalanma nədir?  ",
    "answers": [
      "bədənin yuxarı hissəsini əhatə edən şüalanma  ",
      "yalnız şiş nahiyəsinə verilən şüalanma   46   ",
      "boşluqdaxili verilən şüalanma  ",
      "bütün bədəni əhatə edən şüalanma  ",
      "şiş və müvafiq limfa düyünlərinin daxil olduğu sahəyə verilən şüalanma  "
    ]
 
  }
]